module.v
module StateMach(X, Z, clock, PresA, PresB);

input X;
input clock;
output Z;
reg PresA=0;
reg PresB=0;
output PresA;
output PresB;

wire NexA;
wire NexB;


always@(posedge clock)
begin
    PresA <= NexA;
    PresB <= NexB;
end

//comb

assign NexA = (PresA & (~X))  | (X & PresB);
assign NexB = (~(PresA) & X) | ((~X)&PresB);

endmodule

testbench.v
`timescale 1ns/100ps
module test_SyncCircuit;
wire PresA, PresB;
reg X, clock;

StateMach DUT (X, Z, clock, PresA, PresB);
initial
begin
$dumpfile("test_circuit.vcd");
$dumpvars(0,test_SyncCircuit);
$monitor ("At t=%t, a=%b, b=%b, X=%b, clk=%b,", $time, PresA, PresB, X, clock);
X=1; clock=0;  //t=0
#10 clock=1;

#10 clock=0;
#10 clock=1;
#10 clock=0;
#10 clock=1;
#10 clock=0;
#10 clock=1;
#10 clock=0;
#10 clock=1;
#10 clock=0;
#10 clock=1;
#10 clock=0;
#10 clock=1;
#10 clock=0;
#10 X=0;
#10 clock=1;
#10 clock=0;
#10 clock=1;
#10 clock=0;
#10 clock=1;

#50 $finish;
end


endmodule

test_circuit.vcd
$date
	Mon Apr  1 14:24:24 2024
$end
$version
	Icarus Verilog
$end
$timescale
	100ps
$end
$scope module test_SyncCircuit $end
$var wire 1 ! Z $end
$var wire 1 " PresB $end
$var wire 1 # PresA $end
$var reg 1 $ X $end
$var reg 1 % clock $end
$scope module DUT $end
$var wire 1 & NexA $end
$var wire 1 ' NexB $end
$var wire 1 $ X $end
$var wire 1 ! Z $end
$var wire 1 % clock $end
$var reg 1 # PresA $end
$var reg 1 " PresB $end
$upscope $end
$upscope $end
$enddefinitions $end
$comment Show the parameter values. $end
$dumpall
$end
#0
$dumpvars
1'
0&
0%
1$
0#
0"
z!
$end
#100
1&
1"
1%
#200
0%
#300
0'
1#
1%
#400
0%
#500
0&
0"
1%
#600
0%
#700
1'
0#
1%
#800
0%
#900
1&
1"
1%
#1000
0%
#1100
0'
1#
1%
#1200
0%
#1300
0&
0"
1%
#1400
0%
#1500
1&
0$
